{
    "document_id": -1,
    "url": "https://www.aam-us.org/2018/07/02/net-neutrality-matters-to-museums/",
    "document_category": "News Editorial",
    "annotators": [],
    "author": "Blaire Moskowitz",
    "language": "en",
    "scrape_timestamp": "2020-04-30 18:42:51.144738+00:00",
    "sentences": [
        {
            "id": 0,
            "sentence": "   Privacy notice  This website stores cookies on your computer.",
            "fact": false,
            "misinformation": false,
            "opinion": false,
            "temporal": false,
            "ignore": true,
            "sentence_category": "Uncategorized"
        },
        {
            "id": 1,
            "sentence": "These cookies are used to collect information about how you interact with our website and allow us to remember you.",
            "fact": false,
            "misinformation": false,
            "opinion": false,
            "temporal": false,
            "ignore": true,
            "sentence_category": "Uncategorized"
        },
        {
            "id": 2,
            "sentence": "We use this information in order to improve and customize your browsing experience and for analytics and metrics about our visitors both on this website and other media.",
            "fact": false,
            "misinformation": false,
            "opinion": false,
            "temporal": false,
            "ignore": true,
            "sentence_category": "Uncategorized"
        },
        {
            "id": 3,
            "sentence": "To find out more about the cookies we use, see our .",
            "fact": false,
            "misinformation": false,
            "opinion": false,
            "temporal": false,
            "ignore": true,
            "sentence_category": "Uncategorized"
        },
        {
            "id": 4,
            "sentence": "and dismiss this message Skip to content   AAM Homepage        Site navigation       The following menu has 3 levels.",
            "fact": false,
            "misinformation": false,
            "opinion": false,
            "temporal": false,
            "ignore": true,
            "sentence_category": "Uncategorized"
        },
        {
            "id": 5,
            "sentence": "Press tab to enter the menus and then use your arrow keys, enter, and escape to use the menus.",
            "fact": false,
            "misinformation": false,
            "opinion": false,
            "temporal": false,
            "ignore": true,
            "sentence_category": "Uncategorized"
        },
        {
            "id": 6,
            "sentence": "Please note that items in the second level of these menus can open a page and also expand submenus.",
            "fact": false,
            "misinformation": false,
            "opinion": false,
            "temporal": false,
            "ignore": true,
            "sentence_category": "Uncategorized"
        },
        {
            "id": 7,
            "sentence": "Use left and right arrow keys to navigate between menus.",
            "fact": false,
            "misinformation": false,
            "opinion": false,
            "temporal": false,
            "ignore": true,
            "sentence_category": "Uncategorized"
        },
        {
            "id": 8,
            "sentence": "Use escape to exit.",
            "fact": false,
            "misinformation": false,
            "opinion": false,
            "temporal": false,
            "ignore": true,
            "sentence_category": "Uncategorized"
        },
        {
            "id": 9,
            "sentence": "Use down arrow to open a parent menu.",
            "fact": false,
            "misinformation": false,
            "opinion": false,
            "temporal": false,
            "ignore": true,
            "sentence_category": "Uncategorized"
        },
        {
            "id": 10,
            "sentence": "Within a submenu, Use up and down arrow keys to explore.",
            "fact": false,
            "misinformation": false,
            "opinion": false,
            "temporal": false,
            "ignore": true,
            "sentence_category": "Uncategorized"
        },
        {
            "id": 11,
            "sentence": "Use right arrow key to expand additional submenus.",
            "fact": false,
            "misinformation": false,
            "opinion": false,
            "temporal": false,
            "ignore": true,
            "sentence_category": "Uncategorized"
        },
        {
            "id": 12,
            "sentence": "Use escape to move to parent menu.",
            "fact": false,
            "misinformation": false,
            "opinion": false,
            "temporal": false,
            "ignore": true,
            "sentence_category": "Uncategorized"
        },
        {
            "id": 13,
            "sentence": "Use enter to go to the page.",
            "fact": false,
            "misinformation": false,
            "opinion": false,
            "temporal": false,
            "ignore": true,
            "sentence_category": "Uncategorized"
        },
        {
            "id": 14,
            "sentence": " In future-speak, a “disruptive event” is one that significantly changes the world for good or ill.",
            "fact": false,
            "misinformation": false,
            "opinion": false,
            "temporal": false,
            "ignore": false,
            "sentence_category": "Uncategorized"
        },
        {
            "id": 15,
            "sentence": "Evaluating the ripple effects of such events is an important part of strategic foresight.",
            "fact": false,
            "misinformation": false,
            "opinion": false,
            "temporal": false,
            "ignore": false,
            "sentence_category": "Uncategorized"
        },
        {
            "id": 16,
            "sentence": "For today’s guest post, I invited Blaire Moskowitz, PhD Candidate at the School of Museum Studies at the University of Leicester, to share her opinions on the implications for museums of the recent repeal of regulations that protected net neutrality.",
            "fact": false,
            "misinformation": false,
            "opinion": false,
            "temporal": false,
            "ignore": false,
            "sentence_category": "Uncategorized"
        },
        {
            "id": 17,
            "sentence": "Imagine the following scenarios: Prospective visitors need to pay fees to visit your institution’s website Digital visitors find your website, but it loads excruciatingly slowly While your website’s homepage is available, exhibition microsites and crowdfunding projects are ‘pay-walled’ Now imagine the results.",
            "fact": false,
            "misinformation": false,
            "opinion": false,
            "temporal": false,
            "ignore": false,
            "sentence_category": "Uncategorized"
        },
        {
            "id": 18,
            "sentence": "Think about how these issues would affect your strategic plan.",
            "fact": false,
            "misinformation": false,
            "opinion": false,
            "temporal": false,
            "ignore": false,
            "sentence_category": "Uncategorized"
        },
        {
            "id": 19,
            "sentence": "Previously, Net Neutrality regulations defended the Open Internet by prohibiting Internet Service Providers (ISPs) from charging for specific content and giving certain websites preferred treatment.",
            "fact": false,
            "misinformation": false,
            "opinion": false,
            "temporal": false,
            "ignore": false,
            "sentence_category": "Uncategorized"
        },
        {
            "id": 20,
            "sentence": "Then, on June 11, 2018, the FCC eliminated the regulations and it became legal for ISPs to control what websites are available and to whom.",
            "fact": true,
            "misinformation": false,
            "opinion": false,
            "temporal": false,
            "ignore": false,
            "sentence_category": "Uncategorized"
        },
        {
            "id": 21,
            "sentence": "Skip over related stories to continue reading article COVID-19 Highlighting Museums on #GivingTuesdayNow   For museums, Net Neutrality is especially important once we recognize that digital visitors have significant impact.",
            "fact": false,
            "misinformation": false,
            "opinion": false,
            "temporal": false,
            "ignore": false,
            "sentence_category": "Uncategorized"
        },
        {
            "id": 22,
            "sentence": "These visitors enable us to fulfill our missions and are as important as visitors who cross physical thresholds.",
            "fact": false,
            "misinformation": false,
            "opinion": false,
            "temporal": false,
            "ignore": false,
            "sentence_category": "Uncategorized"
        },
        {
            "id": 23,
            "sentence": "We therefore must fight to continue making our websites available to digital communities at large.",
            "fact": false,
            "misinformation": false,
            "opinion": false,
            "temporal": false,
            "ignore": false,
            "sentence_category": "Uncategorized"
        },
        {
            "id": 24,
            "sentence": "Many museums meet fiscal goals through crowdfunding, which reaches those whose values align with museum missions but may not be nearby.",
            "fact": false,
            "misinformation": false,
            "opinion": false,
            "temporal": false,
            "ignore": false,
            "sentence_category": "Uncategorized"
        },
        {
            "id": 25,
            "sentence": "In addition, digital visitors contribute their time and expertise through crowdsourcing and make a significant impact despite limited resources.",
            "fact": false,
            "misinformation": false,
            "opinion": false,
            "temporal": false,
            "ignore": false,
            "sentence_category": "Uncategorized"
        },
        {
            "id": 26,
            "sentence": "We also need to consider how our institutional narratives are seen by ‘big cable’.",
            "fact": false,
            "misinformation": false,
            "opinion": false,
            "temporal": false,
            "ignore": false,
            "sentence_category": "Uncategorized"
        },
        {
            "id": 27,
            "sentence": "If so, your content about divisive topics could be slowed or censored if ISPs disagree.",
            "fact": false,
            "misinformation": false,
            "opinion": false,
            "temporal": false,
            "ignore": false,
            "sentence_category": "Uncategorized"
        },
        {
            "id": 28,
            "sentence": "Exhibitions may need to include those characters to appease the website-availability-deciders.",
            "fact": false,
            "misinformation": false,
            "opinion": false,
            "temporal": false,
            "ignore": false,
            "sentence_category": "Uncategorized"
        },
        {
            "id": 29,
            "sentence": "For years, museums devoted significant resources to online video series and image databases.",
            "fact": false,
            "misinformation": false,
            "opinion": false,
            "temporal": false,
            "ignore": false,
            "sentence_category": "Uncategorized"
        },
        {
            "id": 30,
            "sentence": "These are only a handful of the issues that could arise.",
            "fact": false,
            "misinformation": false,
            "opinion": false,
            "temporal": false,
            "ignore": false,
            "sentence_category": "Uncategorized"
        },
        {
            "id": 31,
            "sentence": "There are countless more.",
            "fact": false,
            "misinformation": false,
            "opinion": false,
            "temporal": false,
            "ignore": false,
            "sentence_category": "Uncategorized"
        },
        {
            "id": 32,
            "sentence": "The last time Net Neutrality was under threat (in 2014), the internet successfully fought back, including a few museum staffers and organizations taking stands.",
            "fact": true,
            "misinformation": false,
            "opinion": false,
            "temporal": false,
            "ignore": false,
            "sentence_category": "Uncategorized"
        },
        {
            "id": 33,
            "sentence": "But, that was back when the elimination was hypothetical; now, it’s reality.",
            "fact": false,
            "misinformation": false,
            "opinion": false,
            "temporal": false,
            "ignore": false,
            "sentence_category": "Uncategorized"
        },
        {
            "id": 34,
            "sentence": "Within the last year, a few people affiliated with cultural institutions have raised their voice.",
            "fact": false,
            "misinformation": false,
            "opinion": false,
            "temporal": false,
            "ignore": false,
            "sentence_category": "Uncategorized"
        },
        {
            "id": 35,
            "sentence": "Nik Honeysett of BPOC wrote on the topic for Apollo Magazine and I was interviewed by Inverse .",
            "fact": true,
            "misinformation": false,
            "opinion": false,
            "temporal": false,
            "ignore": false,
            "sentence_category": "Uncategorized"
        },
        {
            "id": 36,
            "sentence": "Organizations such as Art21 and Rhizome, have offered comments and a few museums have shared information .",
            "fact": true,
            "misinformation": false,
            "opinion": false,
            "temporal": false,
            "ignore": false,
            "sentence_category": "Uncategorized"
        },
        {
            "id": 37,
            "sentence": "The strongest statements come from two large cultural institutions.",
            "fact": false,
            "misinformation": false,
            "opinion": false,
            "temporal": false,
            "ignore": false,
            "sentence_category": "Uncategorized"
        },
        {
            "id": 38,
            "sentence": "New York Public Libraries affirms that the elimination, “directly impacts the public’s ability to access library collections and materials — the very tools that have helped even the playing field for so many in this country for centuries.” And NYPL’s Tony Marx subsequently called for nonprofits not to be shy about their support.",
            "fact": true,
            "misinformation": false,
            "opinion": false,
            "temporal": false,
            "ignore": false,
            "sentence_category": "Uncategorized"
        },
        {
            "id": 39,
            "sentence": "The strongest museum response was SFMOMA’s call to action .",
            "fact": false,
            "misinformation": false,
            "opinion": false,
            "temporal": false,
            "ignore": false,
            "sentence_category": "Uncategorized"
        },
        {
            "id": 40,
            "sentence": "Their repudiation of the repeal explains, “Intrinsic to SFMOMA’s core mission is making art ‘a vital and meaningful part of public life’.",
            "fact": false,
            "misinformation": false,
            "opinion": false,
            "temporal": false,
            "ignore": false,
            "sentence_category": "Uncategorized"
        },
        {
            "id": 41,
            "sentence": "To that end, SFMOMA strongly supports net neutrality and its corresponding access to cultural and educational initiatives.",
            "fact": false,
            "misinformation": false,
            "opinion": false,
            "temporal": false,
            "ignore": false,
            "sentence_category": "Uncategorized"
        },
        {
            "id": 42,
            "sentence": "There is some hope in the Senate, which passed a resolution to overturn the FCC’s decision against Net Neutrality, though it lacks support in the House.",
            "fact": false,
            "misinformation": false,
            "opinion": false,
            "temporal": false,
            "ignore": false,
            "sentence_category": "Uncategorized"
        },
        {
            "id": 43,
            "sentence": "Similarly, there is hope in state legislatures that have introduced bills to reinstate Net Neutrality, though the legislatures are caving to big cable pressure .",
            "fact": false,
            "misinformation": false,
            "opinion": false,
            "temporal": false,
            "ignore": false,
            "sentence_category": "Uncategorized"
        },
        {
            "id": 44,
            "sentence": "Despite these efforts, it’s not enough.",
            "fact": false,
            "misinformation": false,
            "opinion": false,
            "temporal": false,
            "ignore": false,
            "sentence_category": "Uncategorized"
        },
        {
            "id": 45,
            "sentence": "The entire premise of museums is built on sharing, educating, and preserving culture and it is our responsibility to band together as an industry and fight to share our content online, educate digital visitors and preserve the Open Internet as it was meant to be.",
            "fact": false,
            "misinformation": false,
            "opinion": false,
            "temporal": false,
            "ignore": false,
            "sentence_category": "Uncategorized"
        },
        {
            "id": 46,
            "sentence": "Blaire Moskowitz is a PhD Candidate at the School of Museum Studies at the University of Leicester.",
            "fact": false,
            "misinformation": false,
            "opinion": false,
            "temporal": false,
            "ignore": false,
            "sentence_category": "Uncategorized"
        },
        {
            "id": 47,
            "sentence": "Her research focuses on interactions between museums and digital communities, which discuss the same topics but may or may not intersect online.",
            "fact": false,
            "misinformation": false,
            "opinion": false,
            "temporal": false,
            "ignore": false,
            "sentence_category": "Uncategorized"
        },
        {
            "id": 48,
            "sentence": "She tweets @BlaireMoskowitz and blogs on BlaireMoskowitz.com.",
            "fact": false,
            "misinformation": false,
            "opinion": false,
            "temporal": false,
            "ignore": false,
            "sentence_category": "Uncategorized"
        },
        {
            "id": 49,
            "sentence": "AAM Members get exclusive access to premium digital content including: Featured articles from Access to more than 1,500 resource listings from the Resource Center Tools, reports, and templates for equipping your work in museums Learn more about AAM Membership    We're Sorry   Your current membership level does not allow you to access this content.",
            "fact": false,
            "misinformation": false,
            "opinion": false,
            "temporal": false,
            "ignore": true,
            "sentence_category": "Uncategorized"
        },
        {
            "id": 50,
            "sentence": "TrendsWatch: Museums and the Future of Financial Sustainability   Friday, May 1, 2020   Presented by:    Blackbaud and AAM's Center for the Future of Museums    Tuesday, May 5, 2020   Presented by:    Tuesday, May 5, 2020   Presented by:    AASLH    Wednesday, May 6, 2020   Presented by:    Cancel reply Your email address will not be published.",
            "fact": false,
            "misinformation": false,
            "opinion": false,
            "temporal": false,
            "ignore": true,
            "sentence_category": "Uncategorized"
        },
        {
            "id": 51,
            "sentence": "Required fields are marked * * * Latest Stories from AAM   COVID-19 “The museum we closed will not be the museum we reopen.”   Site footer    The American Alliance of Museums' mission is to champion museums and nurture excellence in partnership with our members and allies.",
            "fact": false,
            "misinformation": false,
            "opinion": false,
            "temporal": false,
            "ignore": true,
            "sentence_category": "Uncategorized"
        },
        {
            "id": 52,
            "sentence": "Footer links        About AAM Social media accounts  LinkedIn       Copyright links        Packed with stories and insights for museum people, Field Notes is delivered to your inbox every Monday.",
            "fact": false,
            "misinformation": false,
            "opinion": false,
            "temporal": false,
            "ignore": true,
            "sentence_category": "Uncategorized"
        },
        {
            "id": 53,
            "sentence": "Once you've completed the form below, confirm your subscription in the email sent to you.",
            "fact": false,
            "misinformation": false,
            "opinion": false,
            "temporal": false,
            "ignore": true,
            "sentence_category": "Uncategorized"
        },
        {
            "id": 54,
            "sentence": "If you are a current AAM member, please sign-up using the email address associated with your account.",
            "fact": false,
            "misinformation": false,
            "opinion": false,
            "temporal": false,
            "ignore": true,
            "sentence_category": "Uncategorized"
        },
        {
            "id": 55,
            "sentence": "Now check your email to confirm your subscription, and please add communications@aam-us.org to your safe sender list.",
            "fact": false,
            "misinformation": false,
            "opinion": false,
            "temporal": false,
            "ignore": true,
            "sentence_category": "Uncategorized"
        }
    ]
}